plannotate/__init__.py
plannotate/annotate.py
plannotate/infernal.py
plannotate/resources.py
plannotate/data/data/colors.csv
plannotate/data/data/databases.yml
plannotate/data/data/feature_orientation.csv
plannotate/data/data/fpbase.csv
plannotate/data/data/protein_existence.csv
plannotate/data/data/snapgene.csv
plannotate/data/data/swissprot.csv.gz
plannotate/data/fastas/RF0G-IodoY.fa
plannotate/data/fastas/pACYC184.fa
plannotate/data/fastas/pBTK562.fa
plannotate/data/fastas/pCA-mTmG.fa
plannotate/data/fastas/pCMVR8.74.fa
plannotate/data/fastas/pPAGFP-C.fa
plannotate/data/fastas/pSC101.fa
plannotate/data/fastas/pTN7-pa1-GFP-Kan.fa
plannotate/data/fastas/pUC19.fa
plannotate/data/fastas/pXampl3.fa
plannotate/data/images/dl_arrow.png
plannotate/data/images/email.b64
plannotate/data/images/github.b64
plannotate/data/images/icon.png
plannotate/data/images/lab.b64
plannotate/data/images/pLannotate.png
plannotate/data/images/paper.b64
plannotate/data/images/twitter.b64
plannotate/data/templates/FAQ.html
plannotate/data/templates/blurb.html
plannotate/data/templates/citation_funding.html
plannotate/data/templates/images.txt
plannotate_python-1.2.9.dist-info/METADATA
plannotate_python-1.2.9.dist-info/WHEEL
plannotate_python-1.2.9.dist-info/licenses/LICENSE
plannotate_python-1.2.9.dist-info/RECORD
