Metadata-Version: 2.4
Name: plannotate-python
Version: 1.2.9
Summary: Automated annotation of engineered plasmids using sequence similarity searches
Project-URL: Homepage, https://github.com/McClain-Thiel/pLannotate
Project-URL: Repository, https://github.com/McClain-Thiel/pLannotate
Project-URL: Bug Tracker, https://github.com/McClain-Thiel/pLannotate/issues
Project-URL: Documentation, https://github.com/McClain-Thiel/pLannotate#readme
Project-URL: Original Project, https://github.com/mmcguffi/pLannotate
Author-email: McClain Thiel <mcclain.thiel@gmail.com>
License: GPL-3.0-or-later
License-File: LICENSE
Keywords: annotation,bioinformatics,molecular-biology,plasmid,sequence-analysis
Classifier: Development Status :: 4 - Beta
Classifier: Environment :: Console
Classifier: Intended Audience :: Science/Research
Classifier: License :: OSI Approved :: GNU General Public License v3 or later (GPLv3+)
Classifier: Operating System :: OS Independent
Classifier: Programming Language :: Python :: 3
Classifier: Programming Language :: Python :: 3.9
Classifier: Programming Language :: Python :: 3.10
Classifier: Programming Language :: Python :: 3.11
Classifier: Programming Language :: Python :: 3.12
Classifier: Topic :: Scientific/Engineering :: Bio-Informatics
Requires-Python: >=3.9
Requires-Dist: biopython>=1.70
Requires-Dist: pandas>=1.0.0
Requires-Dist: platformdirs>=3.0
Requires-Dist: pyyaml>=5.0.0
Requires-Dist: reportlab>=3.5.0
Requires-Dist: tqdm>=4.0.0
Provides-Extra: dev
Requires-Dist: pytest-cov; extra == 'dev'
Requires-Dist: pytest-mock; extra == 'dev'
Requires-Dist: pytest>=6.0; extra == 'dev'
